{
  "header_text1": "MEETING",
  "header_text2": "02-12-2024",
  "main_text1": "MEETING",
  "main_text2": "ROOM",
  "main_name": "ashen",
  "main_time1": "13.00",
  "main_time2": "12.00",
  "second_text1": "MEETING2",
  "second_text2": "COMME",
  "second_name": "ASHEN ",
  "second_time1": "02.00",
  "second_time2": "01.00",
  "time11": "16.00",
  "time12": "11.00",
  "name1": "FINANCE OVW",
  "sub1": "Shehan Anushka",
  "time21": "12.00",
  "time22": "12.00", 
  "name2": "FINANCE OVIEW", 
  "sub2": "Shhan Anushka",
  "time31": "13.00",
  "time32": "14.00",
  "name3": "FIANCE OERVIEW",
  "sub3": "Shhan Anushka",
  "time41": "13.00",
  "time42": "15.00",
  "name4": "FINANCE OERVIEW",
  "sub4": "Shehan Anushka",
  "time51": "14.00",
  "time52": "16.00",
  "name5": "FIANCE OVERVIEW",
  "sub5": "Shhan Aushka",
  "time61": "02.00",
  "time62": "10.00",
  "name6": "FIANCE OVRVIEW",
  "sub6": "Shehane Anuhka",
  "time71": "03.00", 
  "time72": "09.00", 
  "name7": "FIANCEe OVRVIEW", 
  "sub7": "hehane Anushka",
  "time81": "04.00", 
  "time82": "08.00", 
  "name8": "FINeANCE OVERIEW", 
  "sub8": "Sehane Anusha",
  "last_update": "2024-12-29T11:20:00Z"
}
